[
    {
        "lap_number": 1,
        "lap_data": {
            "lap_time": 441.0,
            "fuel_level": 32.96,
            "tire_wear": 0.95,
            "failure": "Tire puncture",
            "weather": "Sunny",
            "tires": "soft",
            "pitstop": "No"
        }
    },
    {
        "lap_number": 2,
        "lap_data": {
            "lap_time": 430.5,
            "fuel_level": 30.92,
            "tire_wear": 0.8999999999999999,
            "failure": "No failure",
            "weather": "Sunny",
            "tires": "soft",
            "pitstop": "No"
        }
    },
    {
        "lap_number": 3,
        "lap_data": {
            "lap_time": 420.0,
            "fuel_level": 28.880000000000003,
            "tire_wear": 0.8499999999999999,
            "failure": "No failure",
            "weather": "Sunny",
            "tires": "soft",
            "pitstop": "No"
        }
    },
    {
        "lap_number": 4,
        "lap_data": {
            "lap_time": 556.5,
            "fuel_level": 26.740000000000002,
            "tire_wear": 0.7999999999999998,
            "failure": "Tire blowout",
            "weather": "Sunny",
            "tires": "soft",
            "pitstop": "No"
        }
    },
    {
        "lap_number": 5,
        "lap_data": {
            "lap_time": 546.0,
            "fuel_level": 24.200000000000003,
            "tire_wear": 0.7499999999999998,
            "failure": "Suspension damage",
            "weather": "Sunny",
            "tires": "soft",
            "pitstop": "No"
        }
    },
    {
        "lap_number": 6,
        "lap_data": {
            "lap_time": 535.5,
            "fuel_level": 21.660000000000004,
            "tire_wear": 0.6999999999999997,
            "failure": "No failure",
            "weather": "Sunny",
            "tires": "soft",
            "pitstop": "No"
        }
    },
    {
        "lap_number": 7,
        "lap_data": {
            "lap_time": 525.0,
            "fuel_level": 19.120000000000005,
            "tire_wear": 0.6499999999999997,
            "failure": "No failure",
            "weather": "Cloudy",
            "tires": "soft",
            "pitstop": "No"
        }
    },
    {
        "lap_number": 8,
        "lap_data": {
            "lap_time": 514.5,
            "fuel_level": 16.580000000000005,
            "tire_wear": 0.5999999999999996,
            "failure": "No failure",
            "weather": "Sunny",
            "tires": "soft",
            "pitstop": "No"
        }
    },
    {
        "lap_number": 9,
        "lap_data": {
            "lap_time": 503.99999999999994,
            "fuel_level": 14.040000000000006,
            "tire_wear": 0.5499999999999996,
            "failure": "No failure",
            "weather": "Sunny",
            "tires": "soft",
            "pitstop": "No"
        }
    },
    {
        "lap_number": 10,
        "lap_data": {
            "lap_time": 3900.5,
            "fuel_level": 35,
            "tire_wear": 1,
            "failure": "No failure",
            "weather": "Cloudy",
            "tires": "soft",
            "pitstop": {
                "repairs": [
                    "Tire puncture",
                    "Tire blowout",
                    "Suspension damage"
                ],
                "fuel_amount": 23.499999999999993,
                "tires_change": true,
                "time in pitstop": 3407.0
            }
        }
    },
    {
        "lap_number": 11,
        "lap_data": {
            "lap_time": 504.0,
            "fuel_level": 32.9,
            "tire_wear": 0.95,
            "failure": "Brakes overheat",
            "weather": "Cloudy",
            "tires": "soft",
            "pitstop": "No"
        }
    },
    {
        "lap_number": 12,
        "lap_data": {
            "lap_time": 577.5,
            "fuel_level": 30.7,
            "tire_wear": 0.8999999999999999,
            "failure": "Tire blowout",
            "weather": "Cloudy",
            "tires": "soft",
            "pitstop": "No"
        }
    },
    {
        "lap_number": 13,
        "lap_data": {
            "lap_time": 567.0,
            "fuel_level": 28.5,
            "tire_wear": 0.8499999999999999,
            "failure": "No failure",
            "weather": "Cloudy",
            "tires": "soft",
            "pitstop": "No"
        }
    },
    {
        "lap_number": 14,
        "lap_data": {
            "lap_time": 598.5,
            "fuel_level": 26.3,
            "tire_wear": 0.7999999999999998,
            "failure": "No failure",
            "weather": "Light rain",
            "tires": "soft",
            "pitstop": "No"
        }
    },
    {
        "lap_number": 15,
        "lap_data": {
            "lap_time": 588.0,
            "fuel_level": 23.900000000000002,
            "tire_wear": 0.7499999999999998,
            "failure": "Cooling system",
            "weather": "Light rain",
            "tires": "soft",
            "pitstop": "No"
        }
    },
    {
        "lap_number": 16,
        "lap_data": {
            "lap_time": 577.5,
            "fuel_level": 21.500000000000004,
            "tire_wear": 0.6999999999999997,
            "failure": "No failure",
            "weather": "Light rain",
            "tires": "soft",
            "pitstop": "No"
        }
    },
    {
        "lap_number": 17,
        "lap_data": {
            "lap_time": 525.0,
            "fuel_level": 19.100000000000005,
            "tire_wear": 0.6499999999999997,
            "failure": "No failure",
            "weather": "Sunny",
            "tires": "soft",
            "pitstop": "No"
        }
    },
    {
        "lap_number": 18,
        "lap_data": {
            "lap_time": 514.5,
            "fuel_level": 16.660000000000004,
            "tire_wear": 0.5999999999999996,
            "failure": "Tire puncture",
            "weather": "Sunny",
            "tires": "soft",
            "pitstop": "No"
        }
    },
    {
        "lap_number": 19,
        "lap_data": {
            "lap_time": 503.99999999999994,
            "fuel_level": 14.120000000000005,
            "tire_wear": 0.5499999999999996,
            "failure": "Brakes overheat",
            "weather": "Sunny",
            "tires": "soft",
            "pitstop": "No"
        }
    },
    {
        "lap_number": 20,
        "lap_data": {
            "lap_time": 3600.34,
            "fuel_level": 35,
            "tire_wear": 1,
            "failure": "No failure",
            "weather": "Sunny",
            "tires": "soft",
            "pitstop": {
                "repairs": [
                    "Brakes overheat",
                    "Tire blowout",
                    "Cooling system",
                    "Tire puncture",
                    "Brakes overheat"
                ],
                "fuel_amount": 23.419999999999995,
                "tires_change": true,
                "time in pitstop": 3106.84
            }
        }
    },
    {
        "lap_number": 21,
        "lap_data": {
            "lap_time": 420.0,
            "fuel_level": 33,
            "tire_wear": 0.95,
            "failure": "No failure",
            "weather": "Sunny",
            "tires": "soft",
            "pitstop": "No"
        }
    },
    {
        "lap_number": 22,
        "lap_data": {
            "lap_time": 409.5,
            "fuel_level": 31,
            "tire_wear": 0.8999999999999999,
            "failure": "No failure",
            "weather": "Sunny",
            "tires": "soft",
            "pitstop": "No"
        }
    },
    {
        "lap_number": 23,
        "lap_data": {
            "lap_time": 399.0,
            "fuel_level": 29,
            "tire_wear": 0.8499999999999999,
            "failure": "No failure",
            "weather": "Sunny",
            "tires": "soft",
            "pitstop": "No"
        }
    },
    {
        "lap_number": 24,
        "lap_data": {
            "lap_time": 388.5,
            "fuel_level": 27,
            "tire_wear": 0.7999999999999998,
            "failure": "No failure",
            "weather": "Sunny",
            "tires": "soft",
            "pitstop": "No"
        }
    },
    {
        "lap_number": 25,
        "lap_data": {
            "lap_time": 378.0,
            "fuel_level": 25,
            "tire_wear": 0.7499999999999998,
            "failure": "No failure",
            "weather": "Sunny",
            "tires": "soft",
            "pitstop": "No"
        }
    },
    {
        "lap_number": 26,
        "lap_data": {
            "lap_time": 367.49999999999994,
            "fuel_level": 23,
            "tire_wear": 0.6999999999999997,
            "failure": "No failure",
            "weather": "Sunny",
            "tires": "soft",
            "pitstop": "No"
        }
    },
    {
        "lap_number": 27,
        "lap_data": {
            "lap_time": 356.99999999999994,
            "fuel_level": 21,
            "tire_wear": 0.6499999999999997,
            "failure": "No failure",
            "weather": "Sunny",
            "tires": "soft",
            "pitstop": "No"
        }
    },
    {
        "lap_number": 28,
        "lap_data": {
            "lap_time": 346.49999999999994,
            "fuel_level": 19,
            "tire_wear": 0.5999999999999996,
            "failure": "No failure",
            "weather": "Sunny",
            "tires": "soft",
            "pitstop": "No"
        }
    },
    {
        "lap_number": 29,
        "lap_data": {
            "lap_time": 335.99999999999994,
            "fuel_level": 17,
            "tire_wear": 0.5499999999999996,
            "failure": "No failure",
            "weather": "Sunny",
            "tires": "soft",
            "pitstop": "No"
        }
    },
    {
        "lap_number": 30,
        "lap_data": {
            "lap_time": 1367.8999999999999,
            "fuel_level": 35,
            "tire_wear": 1,
            "failure": "Cooling system",
            "weather": "Sunny",
            "tires": "soft",
            "pitstop": {
                "repairs": [
                    "Cooling system"
                ],
                "fuel_amount": 20.2,
                "tires_change": true,
                "time in pitstop": 1000.4
            }
        }
    },
    {
        "lap_number": 31,
        "lap_data": {
            "lap_time": 420.0,
            "fuel_level": 33,
            "tire_wear": 0.95,
            "failure": "No failure",
            "weather": "Sunny",
            "tires": "soft",
            "pitstop": "No"
        }
    },
    {
        "lap_number": 32,
        "lap_data": {
            "lap_time": 472.5,
            "fuel_level": 30.7,
            "tire_wear": 0.8999999999999999,
            "failure": "Electronics malfunction",
            "weather": "Sunny",
            "tires": "soft",
            "pitstop": "No"
        }
    },
    {
        "lap_number": 33,
        "lap_data": {
            "lap_time": 462.0,
            "fuel_level": 28.4,
            "tire_wear": 0.8499999999999999,
            "failure": "No failure",
            "weather": "Sunny",
            "tires": "soft",
            "pitstop": "No"
        }
    },
    {
        "lap_number": 34,
        "lap_data": {
            "lap_time": 577.5,
            "fuel_level": 25.099999999999998,
            "tire_wear": 0.7999999999999998,
            "failure": "Gearbox failure",
            "weather": "Sunny",
            "tires": "soft",
            "pitstop": "No"
        }
    },
    {
        "lap_number": 35,
        "lap_data": {
            "lap_time": 567.0,
            "fuel_level": 21.799999999999997,
            "tire_wear": 0.7499999999999998,
            "failure": "No failure",
            "weather": "Sunny",
            "tires": "soft",
            "pitstop": "No"
        }
    },
    {
        "lap_number": 36,
        "lap_data": {
            "lap_time": 556.5,
            "fuel_level": 18.499999999999996,
            "tire_wear": 0.6999999999999997,
            "failure": "No failure",
            "weather": "Sunny",
            "tires": "soft",
            "pitstop": "No"
        }
    },
    {
        "lap_number": 37,
        "lap_data": {
            "lap_time": 546.0,
            "fuel_level": 15.199999999999996,
            "tire_wear": 0.6499999999999997,
            "failure": "No failure",
            "weather": "Sunny",
            "tires": "soft",
            "pitstop": "No"
        }
    },
    {
        "lap_number": 38,
        "lap_data": {
            "lap_time": 535.5,
            "fuel_level": 11.899999999999995,
            "tire_wear": 0.5999999999999996,
            "failure": "No failure",
            "weather": "Sunny",
            "tires": "soft",
            "pitstop": "No"
        }
    },
    {
        "lap_number": 39,
        "lap_data": {
            "lap_time": 524.9999999999999,
            "fuel_level": 8.599999999999994,
            "tire_wear": 0.5499999999999996,
            "failure": "No failure",
            "weather": "Sunny",
            "tires": "soft",
            "pitstop": "No"
        }
    },
    {
        "lap_number": 40,
        "lap_data": {
            "lap_time": 8746.8,
            "fuel_level": 35,
            "tire_wear": 1,
            "failure": "Engine overheating",
            "weather": "Sunny",
            "tires": "soft",
            "pitstop": {
                "repairs": [
                    "Electronics malfunction",
                    "Gearbox failure",
                    "Engine overheating"
                ],
                "fuel_amount": 30.900000000000006,
                "tires_change": true,
                "time in pitstop": 8221.8
            }
        }
    },
    {
        "lap_number": 41,
        "lap_data": {
            "lap_time": 420.0,
            "fuel_level": 33,
            "tire_wear": 0.95,
            "failure": "No failure",
            "weather": "Sunny",
            "tires": "soft",
            "pitstop": "No"
        }
    },
    {
        "lap_number": 42,
        "lap_data": {
            "lap_time": 409.5,
            "fuel_level": 31,
            "tire_wear": 0.8999999999999999,
            "failure": "No failure",
            "weather": "Sunny",
            "tires": "soft",
            "pitstop": "No"
        }
    },
    {
        "lap_number": 43,
        "lap_data": {
            "lap_time": 441.0,
            "fuel_level": 28.8,
            "tire_wear": 0.8499999999999999,
            "failure": "Cooling system",
            "weather": "Sunny",
            "tires": "soft",
            "pitstop": "No"
        }
    },
    {
        "lap_number": 44,
        "lap_data": {
            "lap_time": 430.5,
            "fuel_level": 26.6,
            "tire_wear": 0.7999999999999998,
            "failure": "No failure",
            "weather": "Sunny",
            "tires": "soft",
            "pitstop": "No"
        }
    },
    {
        "lap_number": 45,
        "lap_data": {
            "lap_time": 420.0,
            "fuel_level": 24.400000000000002,
            "tire_wear": 0.7499999999999998,
            "failure": "No failure",
            "weather": "Sunny",
            "tires": "soft",
            "pitstop": "No"
        }
    },
    {
        "lap_number": 46,
        "lap_data": {
            "lap_time": 409.49999999999994,
            "fuel_level": 22.200000000000003,
            "tire_wear": 0.6999999999999997,
            "failure": "No failure",
            "weather": "Sunny",
            "tires": "soft",
            "pitstop": "No"
        }
    },
    {
        "lap_number": 47,
        "lap_data": {
            "lap_time": 398.99999999999994,
            "fuel_level": 20.000000000000004,
            "tire_wear": 0.6499999999999997,
            "failure": "No failure",
            "weather": "Sunny",
            "tires": "soft",
            "pitstop": "No"
        }
    },
    {
        "lap_number": 48,
        "lap_data": {
            "lap_time": 514.5,
            "fuel_level": 17.700000000000003,
            "tire_wear": 0.5999999999999996,
            "failure": "Tire blowout",
            "weather": "Sunny",
            "tires": "soft",
            "pitstop": "No"
        }
    },
    {
        "lap_number": 49,
        "lap_data": {
            "lap_time": 503.99999999999994,
            "fuel_level": 15.400000000000002,
            "tire_wear": 0.5499999999999996,
            "failure": "No failure",
            "weather": "Sunny",
            "tires": "soft",
            "pitstop": "No"
        }
    },
    {
        "lap_number": 50,
        "lap_data": {
            "lap_time": 4498.099999999999,
            "fuel_level": 35,
            "tire_wear": 1,
            "failure": "Suspension damage",
            "weather": "Sunny",
            "tires": "soft",
            "pitstop": {
                "repairs": [
                    "Cooling system",
                    "Tire blowout",
                    "Suspension damage"
                ],
                "fuel_amount": 22.299999999999997,
                "tires_change": true,
                "time in pitstop": 4004.6
            }
        }
    },
    {
        "lap_number": 51,
        "lap_data": {
            "lap_time": 588.0,
            "fuel_level": 32.9,
            "tire_wear": 0.95,
            "failure": "Tire blowout",
            "weather": "Sunny",
            "tires": "soft",
            "pitstop": "No"
        }
    },
    {
        "lap_number": 52,
        "lap_data": {
            "lap_time": 577.5,
            "fuel_level": 30.799999999999997,
            "tire_wear": 0.8999999999999999,
            "failure": "No failure",
            "weather": "Cloudy",
            "tires": "soft",
            "pitstop": "No"
        }
    },
    {
        "lap_number": 53,
        "lap_data": {
            "lap_time": 567.0,
            "fuel_level": 28.699999999999996,
            "tire_wear": 0.8499999999999999,
            "failure": "No failure",
            "weather": "Cloudy",
            "tires": "soft",
            "pitstop": "No"
        }
    },
    {
        "lap_number": 54,
        "lap_data": {
            "lap_time": 556.5,
            "fuel_level": 26.599999999999994,
            "tire_wear": 0.7999999999999998,
            "failure": "No failure",
            "weather": "Cloudy",
            "tires": "soft",
            "pitstop": "No"
        }
    },
    {
        "lap_number": 55,
        "lap_data": {
            "lap_time": 546.0,
            "fuel_level": 24.399999999999995,
            "tire_wear": 0.7499999999999998,
            "failure": "Tire blowout",
            "weather": "Cloudy",
            "tires": "soft",
            "pitstop": "No"
        }
    },
    {
        "lap_number": 56,
        "lap_data": {
            "lap_time": 535.5,
            "fuel_level": 22.099999999999994,
            "tire_wear": 0.6999999999999997,
            "failure": "Brakes overheat",
            "weather": "Cloudy",
            "tires": "soft",
            "pitstop": "No"
        }
    },
    {
        "lap_number": 57,
        "lap_data": {
            "lap_time": 567.0,
            "fuel_level": 19.599999999999994,
            "tire_wear": 0.6499999999999997,
            "failure": "Cooling system",
            "weather": "Light rain",
            "tires": "soft",
            "pitstop": "No"
        }
    },
    {
        "lap_number": 58,
        "lap_data": {
            "lap_time": 556.5,
            "fuel_level": 17.099999999999994,
            "tire_wear": 0.5999999999999996,
            "failure": "No failure",
            "weather": "Light rain",
            "tires": "soft",
            "pitstop": "No"
        }
    },
    {
        "lap_number": 59,
        "lap_data": {
            "lap_time": 629.9999999999999,
            "fuel_level": 14.559999999999995,
            "tire_wear": 0.5499999999999996,
            "failure": "Tire puncture",
            "weather": "Heavy rain",
            "tires": "soft",
            "pitstop": "No"
        }
    },
    {
        "lap_number": 60,
        "lap_data": {
            "lap_time": 4625.86,
            "fuel_level": 35,
            "tire_wear": 1,
            "failure": "Cooling system",
            "weather": "Heavy rain",
            "tires": "soft",
            "pitstop": {
                "repairs": [
                    "Tire blowout",
                    "Tire blowout",
                    "Brakes overheat",
                    "Cooling system",
                    "Tire puncture",
                    "Cooling system"
                ],
                "fuel_amount": 23.180000000000007,
                "tires_change": true,
                "time in pitstop": 4006.36
            }
        }
    },
    {
        "lap_number": 61,
        "lap_data": {
            "lap_time": 546.0,
            "fuel_level": 33,
            "tire_wear": 0.95,
            "failure": "No failure",
            "weather": "Heavy rain",
            "tires": "soft",
            "pitstop": "No"
        }
    },
    {
        "lap_number": 62,
        "lap_data": {
            "lap_time": 703.5,
            "fuel_level": 30.9,
            "tire_wear": 0.8999999999999999,
            "failure": "Tire blowout",
            "weather": "Heavy rain",
            "tires": "soft",
            "pitstop": "No"
        }
    },
    {
        "lap_number": 63,
        "lap_data": {
            "lap_time": 609.0,
            "fuel_level": 28.0,
            "tire_wear": 0.8499999999999999,
            "failure": "Fuel pump issue",
            "weather": "Light rain",
            "tires": "soft",
            "pitstop": "No"
        }
    },
    {
        "lap_number": 64,
        "lap_data": {
            "lap_time": 598.5,
            "fuel_level": 25.1,
            "tire_wear": 0.7999999999999998,
            "failure": "No failure",
            "weather": "Light rain",
            "tires": "soft",
            "pitstop": "No"
        }
    },
    {
        "lap_number": 65,
        "lap_data": {
            "lap_time": 588.0,
            "fuel_level": 22.200000000000003,
            "tire_wear": 0.7499999999999998,
            "failure": "No failure",
            "weather": "Light rain",
            "tires": "soft",
            "pitstop": "No"
        }
    },
    {
        "lap_number": 66,
        "lap_data": {
            "lap_time": 577.5,
            "fuel_level": 19.300000000000004,
            "tire_wear": 0.6999999999999997,
            "failure": "No failure",
            "weather": "Light rain",
            "tires": "soft",
            "pitstop": "No"
        }
    },
    {
        "lap_number": 67,
        "lap_data": {
            "lap_time": 525.0,
            "fuel_level": 16.400000000000006,
            "tire_wear": 0.6499999999999997,
            "failure": "No failure",
            "weather": "Sunny",
            "tires": "soft",
            "pitstop": "No"
        }
    },
    {
        "lap_number": 68,
        "lap_data": {
            "lap_time": 514.5,
            "fuel_level": 13.000000000000005,
            "tire_wear": 0.5999999999999996,
            "failure": "Hydraulic leak",
            "weather": "Cloudy",
            "tires": "soft",
            "pitstop": "No"
        }
    },
    {
        "lap_number": 69,
        "lap_data": {
            "lap_time": 503.99999999999994,
            "fuel_level": 9.600000000000005,
            "tire_wear": 0.5499999999999996,
            "failure": "No failure",
            "weather": "Cloudy",
            "tires": "soft",
            "pitstop": "No"
        }
    },
    {
        "lap_number": 70,
        "lap_data": {
            "lap_time": 4211.099999999999,
            "fuel_level": 35,
            "tire_wear": 1,
            "failure": "No failure",
            "weather": "Cloudy",
            "tires": "soft",
            "pitstop": {
                "repairs": [
                    "Tire blowout",
                    "Fuel pump issue",
                    "Hydraulic leak"
                ],
                "fuel_amount": 28.799999999999997,
                "tires_change": true,
                "time in pitstop": 3717.6
            }
        }
    },
    {
        "lap_number": 71,
        "lap_data": {
            "lap_time": 420,
            "fuel_level": 33,
            "tire_wear": 0.95,
            "failure": "No failure",
            "weather": "Cloudy",
            "tires": "soft",
            "pitstop": "No"
        }
    },
    {
        "lap_number": 72,
        "lap_data": {
            "lap_time": 409.5,
            "fuel_level": 31,
            "tire_wear": 0.8999999999999999,
            "failure": "No failure",
            "weather": "Sunny",
            "tires": "soft",
            "pitstop": "No"
        }
    },
    {
        "lap_number": 73,
        "lap_data": {
            "lap_time": 399.0,
            "fuel_level": 29,
            "tire_wear": 0.8499999999999999,
            "failure": "No failure",
            "weather": "Sunny",
            "tires": "soft",
            "pitstop": "No"
        }
    },
    {
        "lap_number": 74,
        "lap_data": {
            "lap_time": 472.5,
            "fuel_level": 26.9,
            "tire_wear": 0.7999999999999998,
            "failure": "Brakes overheat",
            "weather": "Sunny",
            "tires": "soft",
            "pitstop": "No"
        }
    },
    {
        "lap_number": 75,
        "lap_data": {
            "lap_time": 546.0,
            "fuel_level": 24.7,
            "tire_wear": 0.7499999999999998,
            "failure": "Tire blowout",
            "weather": "Sunny",
            "tires": "soft",
            "pitstop": "No"
        }
    },
    {
        "lap_number": 76,
        "lap_data": {
            "lap_time": 535.5,
            "fuel_level": 22.5,
            "tire_wear": 0.6999999999999997,
            "failure": "No failure",
            "weather": "Sunny",
            "tires": "soft",
            "pitstop": "No"
        }
    },
    {
        "lap_number": 77,
        "lap_data": {
            "lap_time": 525.0,
            "fuel_level": 20.1,
            "tire_wear": 0.6499999999999997,
            "failure": "Cooling system",
            "weather": "Sunny",
            "tires": "soft",
            "pitstop": "No"
        }
    },
    {
        "lap_number": 78,
        "lap_data": {
            "lap_time": 514.5,
            "fuel_level": 17.700000000000003,
            "tire_wear": 0.5999999999999996,
            "failure": "No failure",
            "weather": "Sunny",
            "tires": "soft",
            "pitstop": "No"
        }
    },
    {
        "lap_number": 79,
        "lap_data": {
            "lap_time": 503.99999999999994,
            "fuel_level": 15.000000000000004,
            "tire_wear": 0.5499999999999996,
            "failure": "Electronics malfunction",
            "weather": "Cloudy",
            "tires": "soft",
            "pitstop": "No"
        }
    },
    {
        "lap_number": 80,
        "lap_data": {
            "lap_time": 4198.9,
            "fuel_level": 35,
            "tire_wear": 1,
            "failure": "No failure",
            "weather": "Cloudy",
            "tires": "soft",
            "pitstop": {
                "repairs": [
                    "Brakes overheat",
                    "Tire blowout",
                    "Cooling system",
                    "Electronics malfunction"
                ],
                "fuel_amount": 22.699999999999996,
                "tires_change": true,
                "time in pitstop": 3705.4
            }
        }
    },
    {
        "lap_number": 81,
        "lap_data": {
            "lap_time": 420,
            "fuel_level": 33,
            "tire_wear": 0.95,
            "failure": "No failure",
            "weather": "Cloudy",
            "tires": "soft",
            "pitstop": "No"
        }
    },
    {
        "lap_number": 82,
        "lap_data": {
            "lap_time": 409.5,
            "fuel_level": 31,
            "tire_wear": 0.8999999999999999,
            "failure": "No failure",
            "weather": "Cloudy",
            "tires": "soft",
            "pitstop": "No"
        }
    },
    {
        "lap_number": 83,
        "lap_data": {
            "lap_time": 420.0,
            "fuel_level": 28.96,
            "tire_wear": 0.8499999999999999,
            "failure": "Tire puncture",
            "weather": "Cloudy",
            "tires": "soft",
            "pitstop": "No"
        }
    },
    {
        "lap_number": 84,
        "lap_data": {
            "lap_time": 409.5,
            "fuel_level": 26.92,
            "tire_wear": 0.7999999999999998,
            "failure": "No failure",
            "weather": "Cloudy",
            "tires": "soft",
            "pitstop": "No"
        }
    },
    {
        "lap_number": 85,
        "lap_data": {
            "lap_time": 399.0,
            "fuel_level": 24.880000000000003,
            "tire_wear": 0.7499999999999998,
            "failure": "No failure",
            "weather": "Cloudy",
            "tires": "soft",
            "pitstop": "No"
        }
    },
    {
        "lap_number": 86,
        "lap_data": {
            "lap_time": 514.5,
            "fuel_level": 22.040000000000003,
            "tire_wear": 0.6999999999999997,
            "failure": "Turbo",
            "weather": "Cloudy",
            "tires": "soft",
            "pitstop": "No"
        }
    },
    {
        "lap_number": 87,
        "lap_data": {
            "lap_time": 503.99999999999994,
            "fuel_level": 18.700000000000003,
            "tire_wear": 0.6499999999999997,
            "failure": "Hydraulic leak",
            "weather": "Cloudy",
            "tires": "soft",
            "pitstop": "No"
        }
    },
    {
        "lap_number": 88,
        "lap_data": {
            "lap_time": 493.49999999999994,
            "fuel_level": 15.320000000000002,
            "tire_wear": 0.5999999999999996,
            "failure": "Tire puncture",
            "weather": "Cloudy",
            "tires": "soft",
            "pitstop": "No"
        }
    },
    {
        "lap_number": 89,
        "lap_data": {
            "lap_time": 482.99999999999994,
            "fuel_level": 11.940000000000001,
            "tire_wear": 0.5499999999999996,
            "failure": "No failure",
            "weather": "Cloudy",
            "tires": "soft",
            "pitstop": "No"
        }
    },
    {
        "lap_number": 90,
        "lap_data": {
            "lap_time": 4985.38,
            "fuel_level": 35,
            "tire_wear": 1,
            "failure": "No failure",
            "weather": "Cloudy",
            "tires": "soft",
            "pitstop": {
                "repairs": [
                    "Tire puncture",
                    "Turbo",
                    "Hydraulic leak",
                    "Tire puncture"
                ],
                "fuel_amount": 26.439999999999998,
                "tires_change": true,
                "time in pitstop": 4512.88
            }
        }
    },
    {
        "lap_number": 91,
        "lap_data": {
            "lap_time": 420.0,
            "fuel_level": 33,
            "tire_wear": 0.95,
            "failure": "No failure",
            "weather": "Sunny",
            "tires": "soft",
            "pitstop": "No"
        }
    },
    {
        "lap_number": 92,
        "lap_data": {
            "lap_time": 430.5,
            "fuel_level": 30.96,
            "tire_wear": 0.8999999999999999,
            "failure": "Tire puncture",
            "weather": "Sunny",
            "tires": "soft",
            "pitstop": "No"
        }
    },
    {
        "lap_number": 93,
        "lap_data": {
            "lap_time": 598.5,
            "fuel_level": 27.720000000000002,
            "tire_wear": 0.8499999999999999,
            "failure": "Engine overheating",
            "weather": "Sunny",
            "tires": "soft",
            "pitstop": "No"
        }
    },
    {
        "lap_number": 94,
        "lap_data": {
            "lap_time": 588.0,
            "fuel_level": 24.480000000000004,
            "tire_wear": 0.7999999999999998,
            "failure": "No failure",
            "weather": "Sunny",
            "tires": "soft",
            "pitstop": "No"
        }
    },
    {
        "lap_number": 95,
        "lap_data": {
            "lap_time": 577.5,
            "fuel_level": 21.240000000000006,
            "tire_wear": 0.7499999999999998,
            "failure": "No failure",
            "weather": "Sunny",
            "tires": "soft",
            "pitstop": "No"
        }
    },
    {
        "lap_number": 96,
        "lap_data": {
            "lap_time": 567.0,
            "fuel_level": 18.000000000000007,
            "tire_wear": 0.6999999999999997,
            "failure": "No failure",
            "weather": "Sunny",
            "tires": "soft",
            "pitstop": "No"
        }
    },
    {
        "lap_number": 97,
        "lap_data": {
            "lap_time": 556.5,
            "fuel_level": 14.760000000000007,
            "tire_wear": 0.6499999999999997,
            "failure": "No failure",
            "weather": "Sunny",
            "tires": "soft",
            "pitstop": "No"
        }
    },
    {
        "lap_number": 98,
        "lap_data": {
            "lap_time": 546.0,
            "fuel_level": 11.520000000000007,
            "tire_wear": 0.5999999999999996,
            "failure": "No failure",
            "weather": "Sunny",
            "tires": "soft",
            "pitstop": "No"
        }
    },
    {
        "lap_number": 99,
        "lap_data": {
            "lap_time": 535.4999999999999,
            "fuel_level": 8.280000000000006,
            "tire_wear": 0.5499999999999996,
            "failure": "No failure",
            "weather": "Cloudy",
            "tires": "soft",
            "pitstop": "No"
        }
    },
    {
        "lap_number": 100,
        "lap_data": {
            "lap_time": 5445.52,
            "fuel_level": 35,
            "tire_wear": 1,
            "failure": "Electronics malfunction",
            "weather": "Cloudy",
            "tires": "soft",
            "pitstop": {
                "repairs": [
                    "Tire puncture",
                    "Engine overheating",
                    "Electronics malfunction"
                ],
                "fuel_amount": 30.259999999999994,
                "tires_change": true,
                "time in pitstop": 4920.52
            }
        }
    },
    {
        "lap_number": 101,
        "lap_data": {
            "lap_time": 462.0,
            "fuel_level": 32.8,
            "tire_wear": 0.95,
            "failure": "Cooling system",
            "weather": "Cloudy",
            "tires": "soft",
            "pitstop": "No"
        }
    },
    {
        "lap_number": 102,
        "lap_data": {
            "lap_time": 451.5,
            "fuel_level": 30.599999999999998,
            "tire_wear": 0.8999999999999999,
            "failure": "No failure",
            "weather": "Cloudy",
            "tires": "soft",
            "pitstop": "No"
        }
    },
    {
        "lap_number": 103,
        "lap_data": {
            "lap_time": 441.0,
            "fuel_level": 28.4,
            "tire_wear": 0.8499999999999999,
            "failure": "No failure",
            "weather": "Cloudy",
            "tires": "soft",
            "pitstop": "No"
        }
    },
    {
        "lap_number": 104,
        "lap_data": {
            "lap_time": 430.5,
            "fuel_level": 26.2,
            "tire_wear": 0.7999999999999998,
            "failure": "No failure",
            "weather": "Cloudy",
            "tires": "soft",
            "pitstop": "No"
        }
    },
    {
        "lap_number": 105,
        "lap_data": {
            "lap_time": 420.0,
            "fuel_level": 24.0,
            "tire_wear": 0.7499999999999998,
            "failure": "No failure",
            "weather": "Cloudy",
            "tires": "soft",
            "pitstop": "No"
        }
    },
    {
        "lap_number": 106,
        "lap_data": {
            "lap_time": 409.49999999999994,
            "fuel_level": 21.8,
            "tire_wear": 0.6999999999999997,
            "failure": "No failure",
            "weather": "Cloudy",
            "tires": "soft",
            "pitstop": "No"
        }
    },
    {
        "lap_number": 107,
        "lap_data": {
            "lap_time": 556.5,
            "fuel_level": 18.400000000000002,
            "tire_wear": 0.6499999999999997,
            "failure": "Engine overheating",
            "weather": "Cloudy",
            "tires": "soft",
            "pitstop": "No"
        }
    },
    {
        "lap_number": 108,
        "lap_data": {
            "lap_time": 546.0,
            "fuel_level": 15.000000000000002,
            "tire_wear": 0.5999999999999996,
            "failure": "No failure",
            "weather": "Cloudy",
            "tires": "soft",
            "pitstop": "No"
        }
    },
    {
        "lap_number": 109,
        "lap_data": {
            "lap_time": 535.4999999999999,
            "fuel_level": 11.600000000000001,
            "tire_wear": 0.5499999999999996,
            "failure": "No failure",
            "weather": "Cloudy",
            "tires": "soft",
            "pitstop": "No"
        }
    },
    {
        "lap_number": 110,
        "lap_data": {
            "lap_time": 5138.8,
            "fuel_level": 35,
            "tire_wear": 1,
            "failure": "Tire blowout",
            "weather": "Cloudy",
            "tires": "soft",
            "pitstop": {
                "repairs": [
                    "Cooling system",
                    "Engine overheating",
                    "Tire blowout"
                ],
                "fuel_amount": 26.9,
                "tires_change": true,
                "time in pitstop": 4613.8
            }
        }
    },
    {
        "lap_number": 111,
        "lap_data": {
            "lap_time": 420,
            "fuel_level": 33,
            "tire_wear": 0.95,
            "failure": "No failure",
            "weather": "Cloudy",
            "tires": "soft",
            "pitstop": "No"
        }
    },
    {
        "lap_number": 112,
        "lap_data": {
            "lap_time": 409.5,
            "fuel_level": 31,
            "tire_wear": 0.8999999999999999,
            "failure": "No failure",
            "weather": "Cloudy",
            "tires": "soft",
            "pitstop": "No"
        }
    },
    {
        "lap_number": 113,
        "lap_data": {
            "lap_time": 399.0,
            "fuel_level": 29,
            "tire_wear": 0.8499999999999999,
            "failure": "No failure",
            "weather": "Cloudy",
            "tires": "soft",
            "pitstop": "No"
        }
    },
    {
        "lap_number": 114,
        "lap_data": {
            "lap_time": 472.5,
            "fuel_level": 26.9,
            "tire_wear": 0.7999999999999998,
            "failure": "Brakes overheat",
            "weather": "Cloudy",
            "tires": "soft",
            "pitstop": "No"
        }
    },
    {
        "lap_number": 115,
        "lap_data": {
            "lap_time": 504.0,
            "fuel_level": 24.799999999999997,
            "tire_wear": 0.7499999999999998,
            "failure": "No failure",
            "weather": "Light rain",
            "tires": "soft",
            "pitstop": "No"
        }
    },
    {
        "lap_number": 116,
        "lap_data": {
            "lap_time": 493.49999999999994,
            "fuel_level": 22.699999999999996,
            "tire_wear": 0.6999999999999997,
            "failure": "No failure",
            "weather": "Light rain",
            "tires": "soft",
            "pitstop": "No"
        }
    },
    {
        "lap_number": 117,
        "lap_data": {
            "lap_time": 482.99999999999994,
            "fuel_level": 20.599999999999994,
            "tire_wear": 0.6499999999999997,
            "failure": "No failure",
            "weather": "Light rain",
            "tires": "soft",
            "pitstop": "No"
        }
    },
    {
        "lap_number": 118,
        "lap_data": {
            "lap_time": 472.49999999999994,
            "fuel_level": 18.499999999999993,
            "tire_wear": 0.5999999999999996,
            "failure": "No failure",
            "weather": "Light rain",
            "tires": "soft",
            "pitstop": "No"
        }
    },
    {
        "lap_number": 119,
        "lap_data": {
            "lap_time": 461.99999999999994,
            "fuel_level": 16.199999999999992,
            "tire_wear": 0.5499999999999996,
            "failure": "Cooling system",
            "weather": "Light rain",
            "tires": "soft",
            "pitstop": "No"
        }
    },
    {
        "lap_number": 120,
        "lap_data": {
            "lap_time": 2137.7,
            "fuel_level": 35,
            "tire_wear": 1,
            "failure": "No failure",
            "weather": "Heavy rain",
            "tires": "soft",
            "pitstop": {
                "repairs": [
                    "Brakes overheat",
                    "Cooling system"
                ],
                "fuel_amount": 21.10000000000001,
                "tires_change": true,
                "time in pitstop": 1602.2
            }
        }
    },
    {
        "lap_number": 121,
        "lap_data": {
            "lap_time": 546.0,
            "fuel_level": 33,
            "tire_wear": 0.95,
            "failure": "No failure",
            "weather": "Heavy rain",
            "tires": "soft",
            "pitstop": "No"
        }
    },
    {
        "lap_number": 122,
        "lap_data": {
            "lap_time": 535.5,
            "fuel_level": 31,
            "tire_wear": 0.8999999999999999,
            "failure": "No failure",
            "weather": "Heavy rain",
            "tires": "soft",
            "pitstop": "No"
        }
    },
    {
        "lap_number": 123,
        "lap_data": {
            "lap_time": 441.0,
            "fuel_level": 29,
            "tire_wear": 0.8499999999999999,
            "failure": "No failure",
            "weather": "Light rain",
            "tires": "soft",
            "pitstop": "No"
        }
    },
    {
        "lap_number": 124,
        "lap_data": {
            "lap_time": 430.5,
            "fuel_level": 27,
            "tire_wear": 0.7999999999999998,
            "failure": "No failure",
            "weather": "Light rain",
            "tires": "soft",
            "pitstop": "No"
        }
    },
    {
        "lap_number": 125,
        "lap_data": {
            "lap_time": 504.0,
            "fuel_level": 25,
            "tire_wear": 0.7499999999999998,
            "failure": "No failure",
            "weather": "Heavy rain",
            "tires": "soft",
            "pitstop": "No"
        }
    },
    {
        "lap_number": 126,
        "lap_data": {
            "lap_time": 556.5,
            "fuel_level": 23,
            "tire_wear": 0.6999999999999997,
            "failure": "No failure",
            "weather": "Thunderstorms",
            "tires": "soft",
            "pitstop": "No"
        }
    },
    {
        "lap_number": 127,
        "lap_data": {
            "lap_time": 651.0,
            "fuel_level": 20.2,
            "tire_wear": 0.6499999999999997,
            "failure": "Fuel pump issue",
            "weather": "Thunderstorms",
            "tires": "soft",
            "pitstop": "No"
        }
    },
    {
        "lap_number": 128,
        "lap_data": {
            "lap_time": 577.5,
            "fuel_level": 17.2,
            "tire_wear": 0.5999999999999996,
            "failure": "Cooling system",
            "weather": "Heavy rain",
            "tires": "soft",
            "pitstop": "No"
        }
    },
    {
        "lap_number": 129,
        "lap_data": {
            "lap_time": 608.9999999999999,
            "fuel_level": 13.7,
            "tire_wear": 0.5499999999999996,
            "failure": "Hydraulic leak",
            "weather": "Heavy rain",
            "tires": "soft",
            "pitstop": "No"
        }
    },
    {
        "lap_number": 130,
        "lap_data": {
            "lap_time": 4608.099999999999,
            "fuel_level": 35,
            "tire_wear": 1,
            "failure": "No failure",
            "weather": "Heavy rain",
            "tires": "soft",
            "pitstop": {
                "repairs": [
                    "Fuel pump issue",
                    "Cooling system",
                    "Hydraulic leak"
                ],
                "fuel_amount": 24.8,
                "tires_change": true,
                "time in pitstop": 4009.6
            }
        }
    },
    {
        "lap_number": 131,
        "lap_data": {
            "lap_time": 546.0,
            "fuel_level": 33,
            "tire_wear": 0.95,
            "failure": "No failure",
            "weather": "Heavy rain",
            "tires": "soft",
            "pitstop": "No"
        }
    },
    {
        "lap_number": 132,
        "lap_data": {
            "lap_time": 598.5,
            "fuel_level": 31,
            "tire_wear": 0.8999999999999999,
            "failure": "No failure",
            "weather": "Thunderstorms",
            "tires": "soft",
            "pitstop": "No"
        }
    },
    {
        "lap_number": 133,
        "lap_data": {
            "lap_time": 724.5,
            "fuel_level": 27.8,
            "tire_wear": 0.8499999999999999,
            "failure": "Engine overheating",
            "weather": "Heavy rain",
            "tires": "soft",
            "pitstop": "No"
        }
    },
    {
        "lap_number": 134,
        "lap_data": {
            "lap_time": 714.0,
            "fuel_level": 24.6,
            "tire_wear": 0.7999999999999998,
            "failure": "No failure",
            "weather": "Heavy rain",
            "tires": "soft",
            "pitstop": "No"
        }
    },
    {
        "lap_number": 135,
        "lap_data": {
            "lap_time": 703.5,
            "fuel_level": 21.400000000000002,
            "tire_wear": 0.7499999999999998,
            "failure": "No failure",
            "weather": "Heavy rain",
            "tires": "soft",
            "pitstop": "No"
        }
    },
    {
        "lap_number": 136,
        "lap_data": {
            "lap_time": 609.0,
            "fuel_level": 18.200000000000003,
            "tire_wear": 0.6999999999999997,
            "failure": "No failure",
            "weather": "Light rain",
            "tires": "soft",
            "pitstop": "No"
        }
    },
    {
        "lap_number": 137,
        "lap_data": {
            "lap_time": 556.5,
            "fuel_level": 15.000000000000004,
            "tire_wear": 0.6499999999999997,
            "failure": "No failure",
            "weather": "Sunny",
            "tires": "soft",
            "pitstop": "No"
        }
    },
    {
        "lap_number": 138,
        "lap_data": {
            "lap_time": 546.0,
            "fuel_level": 11.800000000000004,
            "tire_wear": 0.5999999999999996,
            "failure": "No failure",
            "weather": "Sunny",
            "tires": "soft",
            "pitstop": "No"
        }
    },
    {
        "lap_number": 139,
        "lap_data": {
            "lap_time": 535.4999999999999,
            "fuel_level": 8.560000000000004,
            "tire_wear": 0.5499999999999996,
            "failure": "Tire puncture",
            "weather": "Sunny",
            "tires": "soft",
            "pitstop": "No"
        }
    },
    {
        "lap_number": 140,
        "lap_data": {
            "lap_time": 4544.5599999999995,
            "fuel_level": 35,
            "tire_wear": 1,
            "failure": "Brakes overheat",
            "weather": "Sunny",
            "tires": "soft",
            "pitstop": {
                "repairs": [
                    "Engine overheating",
                    "Tire puncture",
                    "Brakes overheat"
                ],
                "fuel_amount": 29.779999999999994,
                "tires_change": true,
                "time in pitstop": 4019.56
            }
        }
    },
    {
        "lap_number": 141,
        "lap_data": {
            "lap_time": 420.0,
            "fuel_level": 33,
            "tire_wear": 0.95,
            "failure": "No failure",
            "weather": "Sunny",
            "tires": "soft",
            "pitstop": "No"
        }
    },
    {
        "lap_number": 142,
        "lap_data": {
            "lap_time": 409.5,
            "fuel_level": 31,
            "tire_wear": 0.8999999999999999,
            "failure": "No failure",
            "weather": "Sunny",
            "tires": "soft",
            "pitstop": "No"
        }
    },
    {
        "lap_number": 143,
        "lap_data": {
            "lap_time": 399.0,
            "fuel_level": 29,
            "tire_wear": 0.8499999999999999,
            "failure": "No failure",
            "weather": "Sunny",
            "tires": "soft",
            "pitstop": "No"
        }
    },
    {
        "lap_number": 144,
        "lap_data": {
            "lap_time": 535.5,
            "fuel_level": 26.5,
            "tire_wear": 0.7999999999999998,
            "failure": "Hydraulic leak",
            "weather": "Sunny",
            "tires": "soft",
            "pitstop": "No"
        }
    },
    {
        "lap_number": 145,
        "lap_data": {
            "lap_time": 525.0,
            "fuel_level": 24.0,
            "tire_wear": 0.7499999999999998,
            "failure": "No failure",
            "weather": "Sunny",
            "tires": "soft",
            "pitstop": "No"
        }
    },
    {
        "lap_number": 146,
        "lap_data": {
            "lap_time": 514.5,
            "fuel_level": 21.5,
            "tire_wear": 0.6999999999999997,
            "failure": "No failure",
            "weather": "Sunny",
            "tires": "soft",
            "pitstop": "No"
        }
    },
    {
        "lap_number": 147,
        "lap_data": {
            "lap_time": 503.99999999999994,
            "fuel_level": 18.8,
            "tire_wear": 0.6499999999999997,
            "failure": "Cooling system",
            "weather": "Sunny",
            "tires": "soft",
            "pitstop": "No"
        }
    },
    {
        "lap_number": 148,
        "lap_data": {
            "lap_time": 493.49999999999994,
            "fuel_level": 16.1,
            "tire_wear": 0.5999999999999996,
            "failure": "No failure",
            "weather": "Sunny",
            "tires": "soft",
            "pitstop": "No"
        }
    },
    {
        "lap_number": 149,
        "lap_data": {
            "lap_time": 482.99999999999994,
            "fuel_level": 13.360000000000001,
            "tire_wear": 0.5499999999999996,
            "failure": "Tire puncture",
            "weather": "Sunny",
            "tires": "soft",
            "pitstop": "No"
        }
    },
    {
        "lap_number": 150,
        "lap_data": {
            "lap_time": 3781.26,
            "fuel_level": 35,
            "tire_wear": 1,
            "failure": "No failure",
            "weather": "Cloudy",
            "tires": "soft",
            "pitstop": {
                "repairs": [
                    "Hydraulic leak",
                    "Cooling system",
                    "Tire puncture"
                ],
                "fuel_amount": 24.38,
                "tires_change": true,
                "time in pitstop": 3308.76
            }
        }
    },
    {
        "lap_number": 151,
        "lap_data": {
            "lap_time": 420,
            "fuel_level": 33,
            "tire_wear": 0.95,
            "failure": "No failure",
            "weather": "Cloudy",
            "tires": "soft",
            "pitstop": "No"
        }
    },
    {
        "lap_number": 152,
        "lap_data": {
            "lap_time": 409.5,
            "fuel_level": 31,
            "tire_wear": 0.8999999999999999,
            "failure": "No failure",
            "weather": "Cloudy",
            "tires": "soft",
            "pitstop": "No"
        }
    },
    {
        "lap_number": 153,
        "lap_data": {
            "lap_time": 399.0,
            "fuel_level": 29,
            "tire_wear": 0.8499999999999999,
            "failure": "No failure",
            "weather": "Cloudy",
            "tires": "soft",
            "pitstop": "No"
        }
    },
    {
        "lap_number": 154,
        "lap_data": {
            "lap_time": 409.5,
            "fuel_level": 26.96,
            "tire_wear": 0.7999999999999998,
            "failure": "Tire puncture",
            "weather": "Cloudy",
            "tires": "soft",
            "pitstop": "No"
        }
    },
    {
        "lap_number": 155,
        "lap_data": {
            "lap_time": 399.0,
            "fuel_level": 24.92,
            "tire_wear": 0.7499999999999998,
            "failure": "No failure",
            "weather": "Cloudy",
            "tires": "soft",
            "pitstop": "No"
        }
    },
    {
        "lap_number": 156,
        "lap_data": {
            "lap_time": 388.49999999999994,
            "fuel_level": 22.880000000000003,
            "tire_wear": 0.6999999999999997,
            "failure": "No failure",
            "weather": "Cloudy",
            "tires": "soft",
            "pitstop": "No"
        }
    },
    {
        "lap_number": 157,
        "lap_data": {
            "lap_time": 377.99999999999994,
            "fuel_level": 20.800000000000004,
            "tire_wear": 0.6499999999999997,
            "failure": "Tire puncture",
            "weather": "Cloudy",
            "tires": "soft",
            "pitstop": "No"
        }
    },
    {
        "lap_number": 158,
        "lap_data": {
            "lap_time": 367.49999999999994,
            "fuel_level": 18.720000000000006,
            "tire_wear": 0.5999999999999996,
            "failure": "No failure",
            "weather": "Sunny",
            "tires": "soft",
            "pitstop": "No"
        }
    },
    {
        "lap_number": 159,
        "lap_data": {
            "lap_time": 356.99999999999994,
            "fuel_level": 16.640000000000008,
            "tire_wear": 0.5499999999999996,
            "failure": "No failure",
            "weather": "Sunny",
            "tires": "soft",
            "pitstop": "No"
        }
    },
    {
        "lap_number": 160,
        "lap_data": {
            "lap_time": 1347.46,
            "fuel_level": 35,
            "tire_wear": 1,
            "failure": "Tire puncture",
            "weather": "Cloudy",
            "tires": "soft",
            "pitstop": {
                "repairs": [
                    "Tire puncture",
                    "Tire puncture",
                    "Tire puncture"
                ],
                "fuel_amount": 20.47999999999999,
                "tires_change": true,
                "time in pitstop": 1000.96
            }
        }
    },
    {
        "lap_number": 161,
        "lap_data": {
            "lap_time": 483.0,
            "fuel_level": 32.7,
            "tire_wear": 0.95,
            "failure": "Electronics malfunction",
            "weather": "Cloudy",
            "tires": "soft",
            "pitstop": "No"
        }
    },
    {
        "lap_number": 162,
        "lap_data": {
            "lap_time": 598.5,
            "fuel_level": 29.400000000000002,
            "tire_wear": 0.8999999999999999,
            "failure": "Gearbox failure",
            "weather": "Cloudy",
            "tires": "soft",
            "pitstop": "No"
        }
    },
    {
        "lap_number": 163,
        "lap_data": {
            "lap_time": 588.0,
            "fuel_level": 26.1,
            "tire_wear": 0.8499999999999999,
            "failure": "No failure",
            "weather": "Cloudy",
            "tires": "soft",
            "pitstop": "No"
        }
    },
    {
        "lap_number": 164,
        "lap_data": {
            "lap_time": 577.5,
            "fuel_level": 22.8,
            "tire_wear": 0.7999999999999998,
            "failure": "No failure",
            "weather": "Sunny",
            "tires": "soft",
            "pitstop": "No"
        }
    },
    {
        "lap_number": 165,
        "lap_data": {
            "lap_time": 567.0,
            "fuel_level": 19.5,
            "tire_wear": 0.7499999999999998,
            "failure": "No failure",
            "weather": "Sunny",
            "tires": "soft",
            "pitstop": "No"
        }
    },
    {
        "lap_number": 166,
        "lap_data": {
            "lap_time": 556.5,
            "fuel_level": 16.2,
            "tire_wear": 0.6999999999999997,
            "failure": "No failure",
            "weather": "Cloudy",
            "tires": "soft",
            "pitstop": "No"
        }
    },
    {
        "lap_number": 167,
        "lap_data": {
            "lap_time": 546.0,
            "fuel_level": 12.899999999999999,
            "tire_wear": 0.6499999999999997,
            "failure": "No failure",
            "weather": "Sunny",
            "tires": "soft",
            "pitstop": "No"
        }
    },
    {
        "lap_number": 168,
        "lap_data": {
            "lap_time": 535.5,
            "fuel_level": 9.599999999999998,
            "tire_wear": 0.5999999999999996,
            "failure": "No failure",
            "weather": "Cloudy",
            "tires": "soft",
            "pitstop": "No"
        }
    },
    {
        "lap_number": 169,
        "lap_data": {
            "lap_time": 524.9999999999999,
            "fuel_level": 6.259999999999998,
            "tire_wear": 0.5499999999999996,
            "failure": "Tire puncture",
            "weather": "Cloudy",
            "tires": "soft",
            "pitstop": "No"
        }
    },
    {
        "lap_number": 170,
        "lap_data": {
            "lap_time": 9051.56,
            "fuel_level": 35,
            "tire_wear": 1,
            "failure": "Engine overheating",
            "weather": "Sunny",
            "tires": "soft",
            "pitstop": {
                "repairs": [
                    "Electronics malfunction",
                    "Gearbox failure",
                    "Tire puncture",
                    "Engine overheating"
                ],
                "fuel_amount": 33.28,
                "tires_change": true,
                "time in pitstop": 8526.56
            }
        }
    },
    {
        "lap_number": 171,
        "lap_data": {
            "lap_time": 420.0,
            "fuel_level": 33,
            "tire_wear": 0.95,
            "failure": "No failure",
            "weather": "Sunny",
            "tires": "soft",
            "pitstop": "No"
        }
    },
    {
        "lap_number": 172,
        "lap_data": {
            "lap_time": 409.5,
            "fuel_level": 31,
            "tire_wear": 0.8999999999999999,
            "failure": "No failure",
            "weather": "Cloudy",
            "tires": "soft",
            "pitstop": "No"
        }
    },
    {
        "lap_number": 173,
        "lap_data": {
            "lap_time": 399.0,
            "fuel_level": 29,
            "tire_wear": 0.8499999999999999,
            "failure": "No failure",
            "weather": "Cloudy",
            "tires": "soft",
            "pitstop": "No"
        }
    },
    {
        "lap_number": 174,
        "lap_data": {
            "lap_time": 388.5,
            "fuel_level": 27,
            "tire_wear": 0.7999999999999998,
            "failure": "No failure",
            "weather": "Sunny",
            "tires": "soft",
            "pitstop": "No"
        }
    }
]